tapipy/__init__.py
tapipy/actors.py
tapipy/configuration.py
tapipy/errors.py
tapipy/resources/openapi_v3-actors.yml
tapipy/resources/openapi_v3-apps.yml
tapipy/resources/openapi_v3-authenticator.yml
tapipy/resources/openapi_v3-files.yml
tapipy/resources/openapi_v3-globus-proxy.yml
tapipy/resources/openapi_v3-jobs.yml
tapipy/resources/openapi_v3-meta.yml
tapipy/resources/openapi_v3-notifications.yml
tapipy/resources/openapi_v3-pgrest.yml
tapipy/resources/openapi_v3-pods.yml
tapipy/resources/openapi_v3-sk.yml
tapipy/resources/openapi_v3-streams.yml
tapipy/resources/openapi_v3-systems.yml
tapipy/resources/openapi_v3-tenants.yml
tapipy/resources/openapi_v3-tokens.yml
tapipy/resources/openapi_v3-workflows.yml
tapipy/resources/resource_etags.json
tapipy/specs/v2-tapis-project-tapipy-main-tapipy-resources-openapi_v3-pods.pickle
tapipy/specs/v2-tapis-project-tapipy-prod-tapipy-resources-openapi_v3-actors.pickle
tapipy/specs/v2-tapis-project-tapipy-prod-tapipy-resources-openapi_v3-apps.pickle
tapipy/specs/v2-tapis-project-tapipy-prod-tapipy-resources-openapi_v3-authenticator.pickle
tapipy/specs/v2-tapis-project-tapipy-prod-tapipy-resources-openapi_v3-files.pickle
tapipy/specs/v2-tapis-project-tapipy-prod-tapipy-resources-openapi_v3-globus-proxy.pickle
tapipy/specs/v2-tapis-project-tapipy-prod-tapipy-resources-openapi_v3-jobs.pickle
tapipy/specs/v2-tapis-project-tapipy-prod-tapipy-resources-openapi_v3-meta.pickle
tapipy/specs/v2-tapis-project-tapipy-prod-tapipy-resources-openapi_v3-notifications.pickle
tapipy/specs/v2-tapis-project-tapipy-prod-tapipy-resources-openapi_v3-pgrest.pickle
tapipy/specs/v2-tapis-project-tapipy-prod-tapipy-resources-openapi_v3-sk.pickle
tapipy/specs/v2-tapis-project-tapipy-prod-tapipy-resources-openapi_v3-streams.pickle
tapipy/specs/v2-tapis-project-tapipy-prod-tapipy-resources-openapi_v3-systems.pickle
tapipy/specs/v2-tapis-project-tapipy-prod-tapipy-resources-openapi_v3-tenants.pickle
tapipy-25.4.0.dist-info/METADATA
tapipy-25.4.0.dist-info/WHEEL
tapipy-25.4.0.dist-info/licenses/LICENSE.md
tapipy-25.4.0.dist-info/RECORD
