Metadata-Version: 2.4
Name: tapipy
Version: 25.4.0
Summary: Python lib for interacting with an instance of the Tapis API Framework
License: BSD-4-Clause
License-File: LICENSE.md
Author: Joe Stubbs
Author-email: jstubbs@tacc.utexas.edu
Maintainer: Joe Stubbs
Maintainer-email: jstubbs@tacc.utexas.edu
Requires-Python: >=3.8,<4.0
Classifier: License :: Other/Proprietary License
Classifier: Programming Language :: Python :: 3
Classifier: Programming Language :: Python :: 3.8
Classifier: Programming Language :: Python :: 3.9
Classifier: Programming Language :: Python :: 3.10
Classifier: Programming Language :: Python :: 3.11
Classifier: Programming Language :: Python :: 3.12
Classifier: Programming Language :: Python :: 3.13
Classifier: Programming Language :: Python :: 3.14
Requires-Dist: PyJWT (>=1.7.1)
Requires-Dist: atomicwrites (>=1.4.0,<2.0.0)
Requires-Dist: certifi (>=2020.11.8)
Requires-Dist: cloudpickle (>=1.6.0)
Requires-Dist: cryptography (>=3.3.2)
Requires-Dist: jsonschema (>=4.8.0,<5.0.0)
Requires-Dist: openapi_core (==0.16.0)
Requires-Dist: openapi_spec_validator (>=0.5.0,<0.6.0)
Requires-Dist: python_dateutil (>=2.5.3,<3.0.0)
Requires-Dist: pyyaml (>=5.4)
Requires-Dist: requests (>=2.20.0,<3.0.0)
Requires-Dist: setuptools (>=21.0.0)
Requires-Dist: six (>=1.10,<2.0)
Requires-Dist: urllib3 (>=2.1.0)
Project-URL: Repository, https://github.com/tapis-project/tapipy
